swarmpal/__init__.py
swarmpal/_api.py
swarmpal/schema.py
swarmpal/cli/__init__.py
swarmpal/cli/commands.py
swarmpal/experimental/__init__.py
swarmpal/experimental/_local_magnetic_model.py
swarmpal/experimental/dsecs_plotting.py
swarmpal/express/__init__.py
swarmpal/express/_pre_configured_runs.py
swarmpal/io/__init__.py
swarmpal/io/_cdf_interface.py
swarmpal/io/_datafetchers.py
swarmpal/io/_paldata.py
swarmpal/io/py.typed
swarmpal/toolboxes/__init__.py
swarmpal/toolboxes/dsecs/__init__.py
swarmpal/toolboxes/dsecs/aux_tools.py
swarmpal/toolboxes/dsecs/dsecs_algorithms.py
swarmpal/toolboxes/dsecs/processes.py
swarmpal/toolboxes/fac/__init__.py
swarmpal/toolboxes/fac/fac_algorithms.py
swarmpal/toolboxes/fac/processes.py
swarmpal/toolboxes/tfa/__init__.py
swarmpal/toolboxes/tfa/plotting.py
swarmpal/toolboxes/tfa/processes.py
swarmpal/toolboxes/tfa/tfalib.py
swarmpal/utils/__init__.py
swarmpal/utils/configs.py
swarmpal/utils/exceptions.py
swarmpal/utils/queries.py
swarmpal-0.2.0.dist-info/entry_points.txt
swarmpal-0.2.0.dist-info/licenses/LICENSE
swarmpal-0.2.0.dist-info/WHEEL
swarmpal-0.2.0.dist-info/METADATA
swarmpal-0.2.0.dist-info/RECORD
