Metadata-Version: 2.4
Name: swarmpal
Version: 0.2.0
Summary: Toolbox for ESA's Swarm mission
Author-email: Ashley Smith <ashley.smith@ed.ac.uk>
Maintainer-email: Ashley Smith <ashley.smith@ed.ac.uk>
Requires-Python: >=3.10
Classifier: License :: OSI Approved :: MIT License
Classifier: Topic :: Scientific/Engineering
Classifier: Intended Audience :: Science/Research
Classifier: Intended Audience :: Developers
Classifier: Operating System :: OS Independent
Classifier: License :: OSI Approved :: MIT License
Classifier: Programming Language :: Python
Classifier: Programming Language :: Python :: 3
Classifier: Programming Language :: Python :: 3.10
Classifier: Programming Language :: Python :: 3.11
Classifier: Development Status :: 4 - Beta
License-File: LICENSE
Requires-Dist: click >= 8.1
Requires-Dist: hapiclient >= 0.2.3
Requires-Dist: jsonschema >= 4.0.0
Requires-Dist: numpy >= 1.26
Requires-Dist: matplotlib >= 3.5
Requires-Dist: pycdfpp >= 0.7
Requires-Dist: pyyaml >= 6.0.0
Requires-Dist: scipy >= 1.8
Requires-Dist: viresclient >= 0.11
Requires-Dist: xarray >= 2024.10.0
Requires-Dist: pytest >=6 ; extra == "dev"
Requires-Dist: nox >=2022 ; extra == "dev"
Requires-Dist: pre-commit ; extra == "dev"
Requires-Dist: pooch ; extra == "dev"
Requires-Dist: sphinx-autobuild ; extra == "dev"
Requires-Dist: pytest-xdist ; extra == "dev"
Requires-Dist: Sphinx>=7.2 ; extra == "docs"
Requires-Dist: myst-nb>=1.0 ; extra == "docs"
Requires-Dist: sphinx-book-theme>=1.1 ; extra == "docs"
Requires-Dist: sphinx_click>=5.0 ; extra == "docs"
Requires-Dist: sphinx_copybutton>=0.5 ; extra == "docs"
Requires-Dist: sphinx-tabs>=3.4.7 ; extra == "docs"
Requires-Dist: sphinx_design>=0.6.1 ; extra == "docs"
Requires-Dist: sphinx-autoapi ; extra == "docs"
Requires-Dist: matplotlib>=3.9 ; extra == "docs"
Requires-Dist: ipywidgets>=8.0 ; extra == "docs"
Requires-Dist: apexpy>=2.1.0 ; extra == "dsecs"
Requires-Dist: pyproj>=3 ; extra == "dsecs"
Requires-Dist: ipywidgets ; extra == "experimental"
Requires-Dist: cartopy ; extra == "experimental"
Requires-Dist: chaosmagpy ; extra == "experimental"
Requires-Dist: pooch ; extra == "experimental"
Requires-Dist: pytest >=6 ; extra == "test"
Requires-Dist: pooch ; extra == "test"
Project-URL: homepage, https://github.com/Swarm-DISC/SwarmPAL
Provides-Extra: dev
Provides-Extra: docs
Provides-Extra: dsecs
Provides-Extra: experimental
Provides-Extra: test
